ssi/__init__.py
ssi/__main__.py
ssi/config.py
ssi/logger.py
ssi/clients/__init__.py
ssi/clients/client_interface.py
ssi/clients/streaming_client.py
ssi/fastapi/__init__.py
ssi/flask/__init__.py
ssi/types/__init__.py
ssi/types/new_client_connected.py
ssi/types/streaming_data_chunk.py
stapesai_ssi-0.0.3.dist-info/LICENSE
stapesai_ssi-0.0.3.dist-info/METADATA
stapesai_ssi-0.0.3.dist-info/WHEEL
stapesai_ssi-0.0.3.dist-info/entry_points.txt
stapesai_ssi-0.0.3.dist-info/top_level.txt
stapesai_ssi-0.0.3.dist-info/RECORD
